mygrid/__init__.py
mygrid/grid.py
mygrid/rnp.py
mygrid/util.py
mygrid/data/conductors.json
mygrid/power_flow/__init__.py
mygrid/power_flow/backward_forward_sweep.py
mygrid/power_flow/backward_forward_sweep_3p.py
mygrid/short_circuit/__init__.py
mygrid/short_circuit/phase_components.py
mygrid/short_circuit/symmetrical_components.py
mygrid-0.3.dist-info/LICENSE
mygrid-0.3.dist-info/METADATA
mygrid-0.3.dist-info/WHEEL
mygrid-0.3.dist-info/top_level.txt
mygrid-0.3.dist-info/RECORD
