Metadata-Version: 2.1
Name: mygrid
Version: 0.3
Summary: A package to represent a electric grid     topology with extensions to make power flow and short circuit     analysis
Home-page: https://github.com/grei-ufc/mygrid
Author: Lucas Melo
Author-email: lucassmelo@dee.ufc.br
License: UNKNOWN
Platform: UNKNOWN
Classifier: Development Status :: 4 - Beta
Classifier: Environment :: Console
Classifier: Intended Audience :: Science/Research
Classifier: License :: OSI Approved :: GNU Lesser General Public License v2 (LGPLv2)
Classifier: Natural Language :: English
Classifier: Operating System :: OS Independent
Classifier: Programming Language :: Python
Classifier: Programming Language :: Python :: 3
Classifier: Programming Language :: Python :: 3.7
Classifier: Topic :: Scientific/Engineering
Requires-Dist: numpy
Requires-Dist: numba
Requires-Dist: pandas
Requires-Dist: terminaltables
Requires-Dist: graphviz
